Metadata-Version: 2.1
Name: aiogram-windows
Version: 0.0.1a0
Summary: windows for aiogram
Home-page: https://github.com/OGURCHINSKIY/aiogram_windows
Author: ogurchinskiy
License: UNKNOWN
Platform: UNKNOWN
Classifier: Programming Language :: Python :: 3
Classifier: License :: OSI Approved :: MIT License
Classifier: Operating System :: OS Independent
Requires-Python: >=3.7
